odoo/addons/test_server_environment/README.rst
odoo/addons/test_server_environment/__init__.py
odoo/addons/test_server_environment/__manifest__.py
odoo/addons/test_server_environment/models/__init__.py
odoo/addons/test_server_environment/models/server_env_test.py
odoo/addons/test_server_environment/security/ir.model.access.csv
odoo/addons/test_server_environment/static/description/icon.png
odoo/addons/test_server_environment/tests/__init__.py
odoo/addons/test_server_environment/tests/test_server_env_mixin.py
odoo/addons/test_server_environment/tests/test_server_env_mixin_inherit.py
odoo11_addon_test_server_environment-11.0.1.0.0.99.dev8.dist-info/METADATA
odoo11_addon_test_server_environment-11.0.1.0.0.99.dev8.dist-info/RECORD
odoo11_addon_test_server_environment-11.0.1.0.0.99.dev8.dist-info/WHEEL
odoo11_addon_test_server_environment-11.0.1.0.0.99.dev8.dist-info/top_level.txt
